setup.py
CydraTrac.egg-info/PKG-INFO
CydraTrac.egg-info/SOURCES.txt
CydraTrac.egg-info/dependency_links.txt
CydraTrac.egg-info/entry_points.txt
CydraTrac.egg-info/namespace_packages.txt
CydraTrac.egg-info/requires.txt
CydraTrac.egg-info/top_level.txt
cydraplugins/__init__.py
cydraplugins/trac/__init__.py
cydraplugins/trac/permission_policy.py