Metadata-Version: 1.0
Name: CydraTrac
Version: 0.2
Summary: Cydra plugin for trac integration
Home-page: http://www.cydra.org
Author: Manuel Stocker
Author-email: mensi@vis.ethz.ch
License: GPL
Keywords: cydra trac
Platform: UNKNOWN
